voronotalt/__init__.py
voronotalt/_voronotalt_python.cpython-39-i386-linux-gnu.so
voronotalt/biopython_interface.py
voronotalt/biotite_interface.py
voronotalt/gemmi_interface.py
voronotalt/pandas_interface.py
voronotalt/voronotalt_python.py
voronotalt-1.1.479.dist-info/METADATA
voronotalt-1.1.479.dist-info/WHEEL
voronotalt-1.1.479.dist-info/top_level.txt
voronotalt-1.1.479.dist-info/RECORD
voronotalt-1.1.479.dist-info/licenses/LICENSE.txt
