Metadata-Version: 2.1
Name: voronotalt
Version: 1.1.479
Summary: Voronota-LT Python bindings via SWIG
Home-page: https://github.com/kliment-olechnovic/voronotalt_python
Author: Kliment Olechnovic
Author-email: kliment.olechnovic@gmail.com
Classifier: Programming Language :: Python :: 3
Classifier: Programming Language :: C++
Classifier: License :: OSI Approved :: MIT License
Classifier: Operating System :: OS Independent
Requires-Python: >=3.6
License-File: LICENSE.txt
